zmon_cli/__init__.py
zmon_cli/__main__.py
zmon_cli/client.py
zmon_cli/config.py
zmon_cli/console.py
zmon_cli/main.py
zmon_cli/output.py
zmon_cli/cmds/__init__.py
zmon_cli/cmds/alert.py
zmon_cli/cmds/check.py
zmon_cli/cmds/command.py
zmon_cli/cmds/dashboard.py
zmon_cli/cmds/data.py
zmon_cli/cmds/downtime.py
zmon_cli/cmds/entity.py
zmon_cli/cmds/grafana.py
zmon_cli/cmds/group.py
zmon_cli/cmds/search.py
zmon_cli/cmds/token.py
zmon_cli-1.1.74.dist-info/DESCRIPTION.rst
zmon_cli-1.1.74.dist-info/METADATA
zmon_cli-1.1.74.dist-info/RECORD
zmon_cli-1.1.74.dist-info/WHEEL
zmon_cli-1.1.74.dist-info/entry_points.txt
zmon_cli-1.1.74.dist-info/metadata.json
zmon_cli-1.1.74.dist-info/top_level.txt
